<?xml version="1.0" encoding="utf-8" ?>
<dwsync>
<file name="jquery.ui.accordion.min.js" server="192.168.170.16/sumc/development/" local="130473911560310913" remote="130547113800000000" Dst="0" />
<file name="jquery-ui.custom.min.js" server="192.168.170.16/sumc/development/" local="130473911560934914" remote="130547113800000000" Dst="0" />
<file name="jquery.ui.autocomplete.min.js" server="192.168.170.16/sumc/development/" local="130473911559842912" remote="130547113800000000" Dst="0" />
<file name="jquery.ui.button.min.js" server="192.168.170.16/sumc/development/" local="130473911559842912" remote="130547113800000000" Dst="0" />
<file name="jquery.ui.core.min.js" server="192.168.170.16/sumc/development/" local="130473911559686911" remote="130547113800000000" Dst="0" />
<file name="jquery.ui.datepicker.min.js" server="192.168.170.16/sumc/development/" local="130473911559530911" remote="130547113800000000" Dst="0" />
<file name="jquery.ui.dialog.min.js" server="192.168.170.16/sumc/development/" local="130473911559062910" remote="130547113800000000" Dst="0" />
<file name="jquery.ui.draggable.min.js" server="192.168.170.16/sumc/development/" local="130473911559062910" remote="130547113800000000" Dst="0" />
<file name="jquery.ui.droppable.min.js" server="192.168.170.16/sumc/development/" local="130473911558750910" remote="130547113800000000" Dst="0" />
<file name="jquery.ui.effect-blind.min.js" server="192.168.170.16/sumc/development/" local="130473911558750910" remote="130547113800000000" Dst="0" />
<file name="jquery.ui.effect-bounce.min.js" server="192.168.170.16/sumc/development/" local="130473911558438909" remote="130547113800000000" Dst="0" />
<file name="jquery.ui.effect-clip.min.js" server="192.168.170.16/sumc/development/" local="130473911558282909" remote="130547113800000000" Dst="0" />
<file name="jquery.ui.effect-drop.min.js" server="192.168.170.16/sumc/development/" local="130473911557970909" remote="130547113800000000" Dst="0" />
<file name="jquery.ui.effect-explode.min.js" server="192.168.170.16/sumc/development/" local="130473911557814908" remote="130547113800000000" Dst="0" />
<file name="jquery.ui.effect-fade.min.js" server="192.168.170.16/sumc/development/" local="130473911557346907" remote="130547113800000000" Dst="0" />
<file name="jquery.ui.effect-fold.min.js" server="192.168.170.16/sumc/development/" local="130473911557190907" remote="130547113800000000" Dst="0" />
<file name="jquery.ui.effect-highlight.min.js" server="192.168.170.16/sumc/development/" local="130473911556878907" remote="130547113800000000" Dst="0" />
<file name="jquery.ui.effect-pulsate.min.js" server="192.168.170.16/sumc/development/" local="130473911556878907" remote="130547113800000000" Dst="0" />
<file name="jquery.ui.effect-scale.min.js" server="192.168.170.16/sumc/development/" local="130473911556722906" remote="130547113800000000" Dst="0" />
<file name="jquery.ui.effect-shake.min.js" server="192.168.170.16/sumc/development/" local="130473911556410906" remote="130547113800000000" Dst="0" />
<file name="jquery.ui.effect-slide.min.js" server="192.168.170.16/sumc/development/" local="130473911556254906" remote="130547113800000000" Dst="0" />
<file name="jquery.ui.effect-transfer.min.js" server="192.168.170.16/sumc/development/" local="130473911556098905" remote="130547113800000000" Dst="0" />
<file name="jquery.ui.effect.min.js" server="192.168.170.16/sumc/development/" local="130473911555942905" remote="130547113800000000" Dst="0" />
<file name="jquery.ui.menu.min.js" server="192.168.170.16/sumc/development/" local="130473911555786905" remote="130547113800000000" Dst="0" />
<file name="jquery.ui.mouse.min.js" server="192.168.170.16/sumc/development/" local="130473911555474904" remote="130547113800000000" Dst="0" />
<file name="jquery.ui.position.min.js" server="192.168.170.16/sumc/development/" local="130473911555318904" remote="130547113800000000" Dst="0" />
<file name="jquery.ui.progressbar.min.js" server="192.168.170.16/sumc/development/" local="130473911555006903" remote="130547113800000000" Dst="0" />
<file name="jquery.ui.resizable.min.js" server="192.168.170.16/sumc/development/" local="130473911555006903" remote="130547113800000000" Dst="0" />
<file name="jquery.ui.selectable.min.js" server="192.168.170.16/sumc/development/" local="130473911554538903" remote="130547113800000000" Dst="0" />
<file name="jquery.ui.slider.min.js" server="192.168.170.16/sumc/development/" local="130473911554538903" remote="130547113800000000" Dst="0" />
<file name="jquery.ui.sortable.min.js" server="192.168.170.16/sumc/development/" local="130473911554226902" remote="130547113800000000" Dst="0" />
<file name="jquery.ui.spinner.min.js" server="192.168.170.16/sumc/development/" local="130473911554226902" remote="130547113800000000" Dst="0" />
<file name="jquery.ui.tabs.min.js" server="192.168.170.16/sumc/development/" local="130473911553758901" remote="130547113800000000" Dst="0" />
<file name="jquery.ui.tooltip.min.js" server="192.168.170.16/sumc/development/" local="130473911553758901" remote="130547113800000000" Dst="0" />
<file name="jquery.ui.widget.min.js" server="192.168.170.16/sumc/development/" local="130473911553446901" remote="130547113800000000" Dst="0" />
</dwsync>